district_energy_model/__init__.py
district_energy_model/cli.py
district_energy_model/dem.py
district_energy_model/dem_calliope.py
district_energy_model/dem_calliope_cc.py
district_energy_model/dem_calliope_clustering.py
district_energy_model/dem_clustering.py
district_energy_model/dem_constants.py
district_energy_model/dem_costs.py
district_energy_model/dem_create_custom_district.py
district_energy_model/dem_demand.py
district_energy_model/dem_emissions.py
district_energy_model/dem_energy_balance.py
district_energy_model/dem_helper.py
district_energy_model/dem_hp_cop_calculation.py
district_energy_model/dem_output.py
district_energy_model/dem_paths.py
district_energy_model/dem_scenarios.py
district_energy_model/dem_supply.py
district_energy_model/dem_techs.py
district_energy_model/model.py
district_energy_model/paths.py
district_energy_model/input_files/__init__.py
district_energy_model/input_files/inputs.py
district_energy_model/techs/__init__.py
district_energy_model/techs/dem_tech_battery_energy_storage.py
district_energy_model/techs/dem_tech_biomass.py
district_energy_model/techs/dem_tech_chp_gt.py
district_energy_model/techs/dem_tech_core.py
district_energy_model/techs/dem_tech_district_heating.py
district_energy_model/techs/dem_tech_electric_heater.py
district_energy_model/techs/dem_tech_gas_boiler.py
district_energy_model/techs/dem_tech_gas_boiler_cp.py
district_energy_model/techs/dem_tech_gas_tank_energy_storage.py
district_energy_model/techs/dem_tech_gas_turbine_cp.py
district_energy_model/techs/dem_tech_grid_supply.py
district_energy_model/techs/dem_tech_heat_exchanger.py
district_energy_model/techs/dem_tech_heat_pump.py
district_energy_model/techs/dem_tech_heat_pump_core.py
district_energy_model/techs/dem_tech_heat_pump_cp.py
district_energy_model/techs/dem_tech_heat_pump_cp_lt.py
district_energy_model/techs/dem_tech_hydro_power.py
district_energy_model/techs/dem_tech_hydrogen.py
district_energy_model/techs/dem_tech_hydrogen_energy_storage.py
district_energy_model-0.1.0rc2.dist-info/METADATA
district_energy_model-0.1.0rc2.dist-info/WHEEL
district_energy_model-0.1.0rc2.dist-info/entry_points.txt
district_energy_model-0.1.0rc2.dist-info/licenses/LICENSE.txt
district_energy_model-0.1.0rc2.dist-info/RECORD
