Metadata-Version: 2.3
Name: district_energy_model
Version: 0.1.0rc2
Summary: District Energy Model
Project-URL: Homepage, https://https://github.com/HSLUDEM/District_Energy_Model
Project-URL: Issues, https://https://github.com/HSLUDEM/District_Energy_Model/issues
Author-email: Ueli Schilt <ueli.schilt@hslu.ch>
License: Apache-2.0
Classifier: Operating System :: OS Independent
Classifier: Programming Language :: Python :: 3
Requires-Python: >=3.8
Provides-Extra: dev
